{"results": [{"decreto_pdf": "", "decreto_nro": null, "fecha_inicio": "", "fecha_fin": "", "id": "1", "funcionario": {"edad": 0, "foto": {"original": "https://goo.gl/7k97nP", "thumbnail_32x32": "https://goo.gl/7k97nP", "thumbnail": "https://goo.gl/7k97nP"}, "apellido": "", "url": "", "uniqueid": "", "nombrepublico": "Abog. Mart\u00edn Gill", "nombre": "Abog. Mart\u00edn Gill", "franjaetaria": "", "genero": "M"}, "cargo": {"superioresids": [], "id": "1", "oficina": "Intendente", "electivo": false, "categoria": {"id": "1", "orden": 10, "nombre": "Intendente", "requiere_declaracion_jurada": true, "nombre_corto": "Intendente"}, "depende_de": "0", "nombre": "Intendente"}}, {"decreto_pdf": "", "decreto_nro": null, "fecha_inicio": "", "fecha_fin": "", "id": "2", "funcionario": {"edad": 0, "foto": {"original": "https://goo.gl/7k97nP", "thumbnail_32x32": "https://goo.gl/7k97nP", "thumbnail": "https://goo.gl/7k97nP"}, "apellido": "", "url": "", "uniqueid": "", "nombrepublico": "Jos\u00e9 Escamilla", "nombre": "Jos\u00e9 Escamilla", "franjaetaria": "", "genero": "M"}, "cargo": {"superioresids": [], "id": "2", "oficina": "Jefe de Asesores del Intendente", "electivo": false, "categoria": {"id": "2", "orden": 10, "nombre": "Jefe de Asesores del Intendente", "requiere_declaracion_jurada": true, "nombre_corto": "Jefe de Asesores del Intendente"}, "depende_de": "4", "nombre": "Jefe de Asesores del Intendente"}}, {"decreto_pdf": "", "decreto_nro": null, "fecha_inicio": "", "fecha_fin": "", "id": "3", "funcionario": {"edad": 0, "foto": {"original": "https://goo.gl/7k97nP", "thumbnail_32x32": "https://goo.gl/7k97nP", "thumbnail": "https://goo.gl/7k97nP"}, "apellido": "", "url": "", "uniqueid": "", "nombrepublico": "Prof. Gerardo Russo", "nombre": "Prof. Gerardo Russo", "franjaetaria": "", "genero": "M"}, "cargo": {"superioresids": [], "id": "3", "oficina": "Coordinador de Asesores del Intendente", "electivo": false, "categoria": {"id": "3", "orden": 10, "nombre": "Coordinador de Asesores del Intendente", "requiere_declaracion_jurada": true, "nombre_corto": "Coordinador de Asesores del Intendente"}, "depende_de": "2", "nombre": "Coordinador de Asesores del Intendente"}}, {"decreto_pdf": "", "decreto_nro": null, "fecha_inicio": "", "fecha_fin": "", "id": "4", "funcionario": {"edad": 0, "foto": {"original": "https://goo.gl/7k97nP", "thumbnail_32x32": "https://goo.gl/7k97nP", "thumbnail": "https://goo.gl/7k97nP"}, "apellido": "", "url": "", "uniqueid": "", "nombrepublico": "Mar\u00eda Celeste Curetti", "nombre": "Mar\u00eda Celeste Curetti", "franjaetaria": "", "genero": "F"}, "cargo": {"superioresids": [], "id": "4", "oficina": "Coordinadora Unidad Intendencia", "electivo": false, "categoria": {"id": "4", "orden": 10, "nombre": "Coordinadora Unidad Intendencia", "requiere_declaracion_jurada": true, "nombre_corto": "Coordinadora Unidad Intendencia"}, "depende_de": "1", "nombre": "Coordinadora Unidad Intendencia"}}, {"decreto_pdf": "", "decreto_nro": null, "fecha_inicio": "", "fecha_fin": "", "id": "5", "funcionario": {"edad": 0, "foto": {"original": "https://goo.gl/7k97nP", "thumbnail_32x32": "https://goo.gl/7k97nP", "thumbnail": "https://goo.gl/7k97nP"}, "apellido": "", "url": "", "uniqueid": "", "nombrepublico": "Periodista Profesional, Eugenia Ramos", "nombre": "Periodista Profesional, Eugenia Ramos", "franjaetaria": "", "genero": "F"}, "cargo": {"superioresids": [], "id": "5", "oficina": "Subsecretaria de Prensa y Comunicaci\u00f3n Institucional", "electivo": false, "categoria": {"id": "5", "orden": 10, "nombre": "Subsecretaria de Prensa y Comunicaci\u00f3n Institucional", "requiere_declaracion_jurada": true, "nombre_corto": "Subsecretaria de Prensa y Comunicaci\u00f3n Institucional"}, "depende_de": "4", "nombre": "Subsecretaria de Prensa y Comunicaci\u00f3n Institucional"}}, {"decreto_pdf": "", "decreto_nro": null, "fecha_inicio": "", "fecha_fin": "", "id": "6", "funcionario": {"edad": 0, "foto": {"original": "https://goo.gl/7k97nP", "thumbnail_32x32": "https://goo.gl/7k97nP", "thumbnail": "https://goo.gl/7k97nP"}, "apellido": "", "url": "", "uniqueid": "", "nombrepublico": "Lic. Muriel Tarantino", "nombre": "Lic. Muriel Tarantino", "franjaetaria": "", "genero": "F"}, "cargo": {"superioresids": [], "id": "6", "oficina": "Directora de Prensa", "electivo": false, "categoria": {"id": "6", "orden": 10, "nombre": "Directora de Prensa", "requiere_declaracion_jurada": true, "nombre_corto": "Directora de Prensa"}, "depende_de": "5", "nombre": "Directora de Prensa"}}, {"decreto_pdf": "", "decreto_nro": null, "fecha_inicio": "", "fecha_fin": "", "id": "7", "funcionario": {"edad": 0, "foto": {"original": "https://goo.gl/7k97nP", "thumbnail_32x32": "https://goo.gl/7k97nP", "thumbnail": "https://goo.gl/7k97nP"}, "apellido": "", "url": "", "uniqueid": "", "nombrepublico": "H\u00e9ctor Bersano", "nombre": "H\u00e9ctor Bersano", "franjaetaria": "", "genero": "M"}, "cargo": {"superioresids": [], "id": "7", "oficina": "Coordinador de Defensa Civil", "electivo": false, "categoria": {"id": "7", "orden": 10, "nombre": "Coordinador de Defensa Civil", "requiere_declaracion_jurada": true, "nombre_corto": "Coordinador de Defensa Civil"}, "depende_de": "4", "nombre": "Coordinador de Defensa Civil"}}, {"decreto_pdf": "", "decreto_nro": null, "fecha_inicio": "", "fecha_fin": "", "id": "8", "funcionario": {"edad": 0, "foto": {"original": "https://goo.gl/7k97nP", "thumbnail_32x32": "https://goo.gl/7k97nP", "thumbnail": "https://goo.gl/7k97nP"}, "apellido": "", "url": "", "uniqueid": "", "nombrepublico": "Diego Olivero", "nombre": "Diego Olivero", "franjaetaria": "", "genero": "M"}, "cargo": {"superioresids": [], "id": "8", "oficina": "Coordinador General de Gesti\u00f3n de Riesgo y Defensa Civil", "electivo": false, "categoria": {"id": "8", "orden": 10, "nombre": "Coordinador General de Gesti\u00f3n de Riesgo y Defensa Civil", "requiere_declaracion_jurada": true, "nombre_corto": "Coordinador General de Gesti\u00f3n de Riesgo y Defensa Civil"}, "depende_de": "4", "nombre": "Coordinador General de Gesti\u00f3n de Riesgo y Defensa Civil"}}, {"decreto_pdf": "", "decreto_nro": null, "fecha_inicio": "", "fecha_fin": "", "id": "9", "funcionario": {"edad": 0, "foto": {"original": "https://goo.gl/7k97nP", "thumbnail_32x32": "https://goo.gl/7k97nP", "thumbnail": "https://goo.gl/7k97nP"}, "apellido": "", "url": "", "uniqueid": "", "nombrepublico": "Miriam Tessore", "nombre": "Miriam Tessore", "franjaetaria": "", "genero": "F"}, "cargo": {"superioresids": [], "id": "9", "oficina": "Directora de Ceremonial y Protocolo", "electivo": false, "categoria": {"id": "9", "orden": 10, "nombre": "Directora de Ceremonial y Protocolo", "requiere_declaracion_jurada": true, "nombre_corto": "Directora de Ceremonial y Protocolo"}, "depende_de": "4", "nombre": "Directora de Ceremonial y Protocolo"}}, {"decreto_pdf": "", "decreto_nro": null, "fecha_inicio": "", "fecha_fin": "", "id": "10", "funcionario": {"edad": 0, "foto": {"original": "https://goo.gl/7k97nP", "thumbnail_32x32": "https://goo.gl/7k97nP", "thumbnail": "https://goo.gl/7k97nP"}, "apellido": "", "url": "", "uniqueid": "", "nombrepublico": "Dr. Miguel Sponer", "nombre": "Dr. Miguel Sponer", "franjaetaria": "", "genero": "M"}, "cargo": {"superioresids": [], "id": "10", "oficina": "Director de Relaciones P\u00fablicas", "electivo": false, "categoria": {"id": "10", "orden": 10, "nombre": "Director de Relaciones P\u00fablicas", "requiere_declaracion_jurada": true, "nombre_corto": "Director de Relaciones P\u00fablicas"}, "depende_de": "4", "nombre": "Director de Relaciones P\u00fablicas"}}, {"decreto_pdf": "", "decreto_nro": null, "fecha_inicio": "", "fecha_fin": "", "id": "11", "funcionario": {"edad": 0, "foto": {"original": "https://goo.gl/7k97nP", "thumbnail_32x32": "https://goo.gl/7k97nP", "thumbnail": "https://goo.gl/7k97nP"}, "apellido": "", "url": "", "uniqueid": "", "nombrepublico": "Dr. H\u00e9ctor Mu\u00f1oz", "nombre": "Dr. H\u00e9ctor Mu\u00f1oz", "franjaetaria": "", "genero": "M"}, "cargo": {"superioresids": [], "id": "11", "oficina": "Jefe de Gabinete", "electivo": false, "categoria": {"id": "11", "orden": 10, "nombre": "Jefe de Gabinete", "requiere_declaracion_jurada": true, "nombre_corto": "Jefe de Gabinete"}, "depende_de": "1", "nombre": "Jefe de Gabinete"}}, {"decreto_pdf": "", "decreto_nro": null, "fecha_inicio": "", "fecha_fin": "", "id": "12", "funcionario": {"edad": 0, "foto": {"original": "https://goo.gl/7k97nP", "thumbnail_32x32": "https://goo.gl/7k97nP", "thumbnail": "https://goo.gl/7k97nP"}, "apellido": "", "url": "", "uniqueid": "", "nombrepublico": "Lic. Lucas Pagliero", "nombre": "Lic. Lucas Pagliero", "franjaetaria": "", "genero": "M"}, "cargo": {"superioresids": [], "id": "12", "oficina": "Subsecretario de Descentralizaci\u00f3n Territorial", "electivo": false, "categoria": {"id": "12", "orden": 10, "nombre": "Subsecretario de Descentralizaci\u00f3n Territorial", "requiere_declaracion_jurada": true, "nombre_corto": "Subsecretario de Descentralizaci\u00f3n Territorial"}, "depende_de": "11", "nombre": "Subsecretario de Descentralizaci\u00f3n Territorial"}}, {"decreto_pdf": "", "decreto_nro": null, "fecha_inicio": "", "fecha_fin": "", "id": "13", "funcionario": {"edad": 0, "foto": {"original": "https://goo.gl/7k97nP", "thumbnail_32x32": "https://goo.gl/7k97nP", "thumbnail": "https://goo.gl/7k97nP"}, "apellido": "", "url": "", "uniqueid": "", "nombrepublico": "Sebasti\u00e1n Capurro", "nombre": "Sebasti\u00e1n Capurro", "franjaetaria": "", "genero": "M"}, "cargo": {"superioresids": [], "id": "13", "oficina": "Coordinador de Abordajes Territoriales e Identidad", "electivo": false, "categoria": {"id": "13", "orden": 10, "nombre": "Coordinador de Abordajes Territoriales e Identidad", "requiere_declaracion_jurada": true, "nombre_corto": "Coordinador de Abordajes Territoriales e Identidad"}, "depende_de": "11", "nombre": "Coordinador de Abordajes Territoriales e Identidad"}}, {"decreto_pdf": "", "decreto_nro": null, "fecha_inicio": "", "fecha_fin": "", "id": "14", "funcionario": {"edad": 0, "foto": {"original": "https://goo.gl/7k97nP", "thumbnail_32x32": "https://goo.gl/7k97nP", "thumbnail": "https://goo.gl/7k97nP"}, "apellido": "", "url": "", "uniqueid": "", "nombrepublico": "Mario Cortez", "nombre": "Mario Cortez", "franjaetaria": "", "genero": "M"}, "cargo": {"superioresids": [], "id": "14", "oficina": "Director del Municerca N\u00ba 1", "electivo": false, "categoria": {"id": "14", "orden": 10, "nombre": "Director del Municerca N\u00ba 1", "requiere_declaracion_jurada": true, "nombre_corto": "Director del Municerca N\u00ba 1"}, "depende_de": "12", "nombre": "Director del Municerca N\u00ba 1"}}, {"decreto_pdf": "", "decreto_nro": null, "fecha_inicio": "", "fecha_fin": "", "id": "15", "funcionario": {"edad": 0, "foto": {"original": "https://goo.gl/7k97nP", "thumbnail_32x32": "https://goo.gl/7k97nP", "thumbnail": "https://goo.gl/7k97nP"}, "apellido": "", "url": "", "uniqueid": "", "nombrepublico": "Lic. Dami\u00e1n Pablo Truccone", "nombre": "Lic. Dami\u00e1n Pablo Truccone", "franjaetaria": "", "genero": "M"}, "cargo": {"superioresids": [], "id": "15", "oficina": "Director del Municerca N\u00ba 2", "electivo": false, "categoria": {"id": "15", "orden": 10, "nombre": "Director del Municerca N\u00ba 2", "requiere_declaracion_jurada": true, "nombre_corto": "Director del Municerca N\u00ba 2"}, "depende_de": "12", "nombre": "Director del Municerca N\u00ba 2"}}, {"decreto_pdf": "", "decreto_nro": null, "fecha_inicio": "", "fecha_fin": "", "id": "16", "funcionario": {"edad": 0, "foto": {"original": "https://goo.gl/7k97nP", "thumbnail_32x32": "https://goo.gl/7k97nP", "thumbnail": "https://goo.gl/7k97nP"}, "apellido": "", "url": "", "uniqueid": "", "nombrepublico": "Marta Giusti", "nombre": "Marta Giusti", "franjaetaria": "", "genero": "F"}, "cargo": {"superioresids": [], "id": "16", "oficina": "Director del Municerca N\u00ba 3", "electivo": false, "categoria": {"id": "16", "orden": 10, "nombre": "Director del Municerca N\u00ba 3", "requiere_declaracion_jurada": true, "nombre_corto": "Director del Municerca N\u00ba 3"}, "depende_de": "12", "nombre": "Director del Municerca N\u00ba 3"}}, {"decreto_pdf": "", "decreto_nro": null, "fecha_inicio": "", "fecha_fin": "", "id": "17", "funcionario": {"edad": 0, "foto": {"original": "https://goo.gl/7k97nP", "thumbnail_32x32": "https://goo.gl/7k97nP", "thumbnail": "https://goo.gl/7k97nP"}, "apellido": "", "url": "", "uniqueid": "", "nombrepublico": "Oscar Cabrignac", "nombre": "Oscar Cabrignac", "franjaetaria": "", "genero": "M"}, "cargo": {"superioresids": [], "id": "17", "oficina": "Director del Municerca N\u00ba 4", "electivo": false, "categoria": {"id": "17", "orden": 10, "nombre": "Director del Municerca N\u00ba 4", "requiere_declaracion_jurada": true, "nombre_corto": "Director del Municerca N\u00ba 4"}, "depende_de": "12", "nombre": "Director del Municerca N\u00ba 4"}}, {"decreto_pdf": "", "decreto_nro": null, "fecha_inicio": "", "fecha_fin": "", "id": "18", "funcionario": {"edad": 0, "foto": {"original": "https://goo.gl/7k97nP", "thumbnail_32x32": "https://goo.gl/7k97nP", "thumbnail": "https://goo.gl/7k97nP"}, "apellido": "", "url": "", "uniqueid": "", "nombrepublico": "Jorge Barrera", "nombre": "Jorge Barrera", "franjaetaria": "", "genero": "M"}, "cargo": {"superioresids": [], "id": "18", "oficina": "Director del Municerca N\u00ba 5", "electivo": false, "categoria": {"id": "18", "orden": 10, "nombre": "Director del Municerca N\u00ba 5", "requiere_declaracion_jurada": true, "nombre_corto": "Director del Municerca N\u00ba 5"}, "depende_de": "12", "nombre": "Director del Municerca N\u00ba 5"}}, {"decreto_pdf": "", "decreto_nro": null, "fecha_inicio": "", "fecha_fin": "", "id": "19", "funcionario": {"edad": 0, "foto": {"original": "https://goo.gl/7k97nP", "thumbnail_32x32": "https://goo.gl/7k97nP", "thumbnail": "https://goo.gl/7k97nP"}, "apellido": "", "url": "", "uniqueid": "", "nombrepublico": "Mauro Almir\u00f3n", "nombre": "Mauro Almir\u00f3n", "franjaetaria": "", "genero": "M"}, "cargo": {"superioresids": [], "id": "19", "oficina": "Director del Municerca N\u00ba 6", "electivo": false, "categoria": {"id": "19", "orden": 10, "nombre": "Director del Municerca N\u00ba 6", "requiere_declaracion_jurada": true, "nombre_corto": "Director del Municerca N\u00ba 6"}, "depende_de": "12", "nombre": "Director del Municerca N\u00ba 6"}}, {"decreto_pdf": "", "decreto_nro": null, "fecha_inicio": "", "fecha_fin": "", "id": "20", "funcionario": {"edad": 0, "foto": {"original": "https://goo.gl/7k97nP", "thumbnail_32x32": "https://goo.gl/7k97nP", "thumbnail": "https://goo.gl/7k97nP"}, "apellido": "", "url": "", "uniqueid": "", "nombrepublico": "Andr\u00e9s Cer\u00f3n", "nombre": "Andr\u00e9s Cer\u00f3n", "franjaetaria": "", "genero": "M"}, "cargo": {"superioresids": [], "id": "20", "oficina": "Director del Municerca N\u00ba 7", "electivo": false, "categoria": {"id": "20", "orden": 10, "nombre": "Director del Municerca N\u00ba 7", "requiere_declaracion_jurada": true, "nombre_corto": "Director del Municerca N\u00ba 7"}, "depende_de": "12", "nombre": "Director del Municerca N\u00ba 7"}}, {"decreto_pdf": "", "decreto_nro": null, "fecha_inicio": "", "fecha_fin": "", "id": "21", "funcionario": {"edad": 0, "foto": {"original": "https://goo.gl/7k97nP", "thumbnail_32x32": "https://goo.gl/7k97nP", "thumbnail": "https://goo.gl/7k97nP"}, "apellido": "", "url": "", "uniqueid": "", "nombrepublico": "Ing. Christian Seppey", "nombre": "Ing. Christian Seppey", "franjaetaria": "", "genero": "M"}, "cargo": {"superioresids": [], "id": "21", "oficina": "Subsecretario de Informaci\u00f3n y Comunicaciones TIC", "electivo": false, "categoria": {"id": "21", "orden": 10, "nombre": "Subsecretario de Informaci\u00f3n y Comunicaciones TIC", "requiere_declaracion_jurada": true, "nombre_corto": "Subsecretario de Informaci\u00f3n y Comunicaciones TIC"}, "depende_de": "11", "nombre": "Subsecretario de Informaci\u00f3n y Comunicaciones TIC"}}, {"decreto_pdf": "", "decreto_nro": null, "fecha_inicio": "", "fecha_fin": "", "id": "22", "funcionario": {"edad": 0, "foto": {"original": "https://goo.gl/7k97nP", "thumbnail_32x32": "https://goo.gl/7k97nP", "thumbnail": "https://goo.gl/7k97nP"}, "apellido": "", "url": "", "uniqueid": "", "nombrepublico": "\u00c1ngel Quaglia", "nombre": "\u00c1ngel Quaglia", "franjaetaria": "", "genero": "M"}, "cargo": {"superioresids": [], "id": "22", "oficina": "Director de Gesti\u00f3n Administrativa y Rendici\u00f3n de Programas con Fondos de otra Jurisdicci\u00f3n", "electivo": false, "categoria": {"id": "22", "orden": 10, "nombre": "Director de Gesti\u00f3n Administrativa y Rendici\u00f3n de Programas con Fondos de otra Jurisdicci\u00f3n", "requiere_declaracion_jurada": true, "nombre_corto": "Director de Gesti\u00f3n Administrativa y Rendici\u00f3n de Programas con Fondos de otra Jurisdicci\u00f3n"}, "depende_de": "11", "nombre": "Director de Gesti\u00f3n Administrativa y Rendici\u00f3n de Programas con Fondos de otra Jurisdicci\u00f3n"}}, {"decreto_pdf": "", "decreto_nro": null, "fecha_inicio": "", "fecha_fin": "", "id": "23", "funcionario": {"edad": 0, "foto": {"original": "https://goo.gl/7k97nP", "thumbnail_32x32": "https://goo.gl/7k97nP", "thumbnail": "https://goo.gl/7k97nP"}, "apellido": "", "url": "", "uniqueid": "", "nombrepublico": "Mar\u00eda Fernanda Gili", "nombre": "Mar\u00eda Fernanda Gili", "franjaetaria": "", "genero": "F"}, "cargo": {"superioresids": [], "id": "23", "oficina": "Directora de Relaciones Institucionales y Capacitaci\u00f3n", "electivo": false, "categoria": {"id": "23", "orden": 10, "nombre": "Directora de Relaciones Institucionales y Capacitaci\u00f3n", "requiere_declaracion_jurada": true, "nombre_corto": "Directora de Relaciones Institucionales y Capacitaci\u00f3n"}, "depende_de": "11", "nombre": "Directora de Relaciones Institucionales y Capacitaci\u00f3n"}}, {"decreto_pdf": "", "decreto_nro": null, "fecha_inicio": "", "fecha_fin": "", "id": "24", "funcionario": {"edad": 0, "foto": {"original": "https://goo.gl/7k97nP", "thumbnail_32x32": "https://goo.gl/7k97nP", "thumbnail": "https://goo.gl/7k97nP"}, "apellido": "", "url": "", "uniqueid": "", "nombrepublico": "Ing. Agr. Otto Wester", "nombre": "Ing. Agr. Otto Wester", "franjaetaria": "", "genero": "M"}, "cargo": {"superioresids": [], "id": "24", "oficina": "Coordinador de Proyectos y Cooperaci\u00f3n Internacional", "electivo": false, "categoria": {"id": "24", "orden": 10, "nombre": "Coordinador de Proyectos y Cooperaci\u00f3n Internacional", "requiere_declaracion_jurada": true, "nombre_corto": "Coordinador de Proyectos y Cooperaci\u00f3n Internacional"}, "depende_de": "11", "nombre": "Coordinador de Proyectos y Cooperaci\u00f3n Internacional"}}, {"decreto_pdf": "", "decreto_nro": null, "fecha_inicio": "", "fecha_fin": "", "id": "25", "funcionario": {"edad": 0, "foto": {"original": "https://goo.gl/7k97nP", "thumbnail_32x32": "https://goo.gl/7k97nP", "thumbnail": "https://goo.gl/7k97nP"}, "apellido": "", "url": "", "uniqueid": "", "nombrepublico": "Ing. Carlos Ram\u00edrez", "nombre": "Ing. Carlos Ram\u00edrez", "franjaetaria": "", "genero": "M"}, "cargo": {"superioresids": [], "id": "25", "oficina": "Secretario de Desarrollo Urbano, Ambiente e Infraestructura", "electivo": false, "categoria": {"id": "25", "orden": 10, "nombre": "Secretario de Desarrollo Urbano, Ambiente e Infraestructura", "requiere_declaracion_jurada": true, "nombre_corto": "Secretario de Desarrollo Urbano, Ambiente e Infraestructura"}, "depende_de": "1", "nombre": "Secretario de Desarrollo Urbano, Ambiente e Infraestructura"}}, {"decreto_pdf": "", "decreto_nro": null, "fecha_inicio": "", "fecha_fin": "", "id": "26", "funcionario": {"edad": 0, "foto": {"original": "https://goo.gl/7k97nP", "thumbnail_32x32": "https://goo.gl/7k97nP", "thumbnail": "https://goo.gl/7k97nP"}, "apellido": "", "url": "", "uniqueid": "", "nombrepublico": "Omar Regueira", "nombre": "Omar Regueira", "franjaetaria": "", "genero": "M"}, "cargo": {"superioresids": [], "id": "26", "oficina": "Subsecretario de Desarrollo Urbano, Ambiente e Infraestructura", "electivo": false, "categoria": {"id": "26", "orden": 10, "nombre": "Subsecretario de Desarrollo Urbano, Ambiente e Infraestructura", "requiere_declaracion_jurada": true, "nombre_corto": "Subsecretario de Desarrollo Urbano, Ambiente e Infraestructura"}, "depende_de": "25", "nombre": "Subsecretario de Desarrollo Urbano, Ambiente e Infraestructura"}}, {"decreto_pdf": "", "decreto_nro": null, "fecha_inicio": "", "fecha_fin": "", "id": "27", "funcionario": {"edad": 0, "foto": {"original": "https://goo.gl/7k97nP", "thumbnail_32x32": "https://goo.gl/7k97nP", "thumbnail": "https://goo.gl/7k97nP"}, "apellido": "", "url": "", "uniqueid": "", "nombrepublico": "Arq. Soledad Monge", "nombre": "Arq. Soledad Monge", "franjaetaria": "", "genero": "F"}, "cargo": {"superioresids": [], "id": "27", "oficina": "Directora de Proyectos de Obra P\u00fablica", "electivo": false, "categoria": {"id": "27", "orden": 10, "nombre": "Directora de Proyectos de Obra P\u00fablica", "requiere_declaracion_jurada": true, "nombre_corto": "Directora de Proyectos de Obra P\u00fablica"}, "depende_de": "26", "nombre": "Directora de Proyectos de Obra P\u00fablica"}}, {"decreto_pdf": "", "decreto_nro": null, "fecha_inicio": "", "fecha_fin": "", "id": "28", "funcionario": {"edad": 0, "foto": {"original": "https://goo.gl/7k97nP", "thumbnail_32x32": "https://goo.gl/7k97nP", "thumbnail": "https://goo.gl/7k97nP"}, "apellido": "", "url": "", "uniqueid": "", "nombrepublico": "Ge\u00f3logo Germ\u00e1n Tissera", "nombre": "Ge\u00f3logo Germ\u00e1n Tissera", "franjaetaria": "", "genero": "M"}, "cargo": {"superioresids": [], "id": "28", "oficina": "Director de Medioambiente y Saneamiento", "electivo": false, "categoria": {"id": "28", "orden": 10, "nombre": "Director de Medioambiente y Saneamiento", "requiere_declaracion_jurada": true, "nombre_corto": "Director de Medioambiente y Saneamiento"}, "depende_de": "26", "nombre": "Director de Medioambiente y Saneamiento"}}, {"decreto_pdf": "", "decreto_nro": null, "fecha_inicio": "", "fecha_fin": "", "id": "29", "funcionario": {"edad": 0, "foto": {"original": "https://goo.gl/7k97nP", "thumbnail_32x32": "https://goo.gl/7k97nP", "thumbnail": "https://goo.gl/7k97nP"}, "apellido": "", "url": "", "uniqueid": "", "nombrepublico": "Ing. Eduardo Mart\u00ednez", "nombre": "Ing. Eduardo Mart\u00ednez", "franjaetaria": "", "genero": "M"}, "cargo": {"superioresids": [], "id": "29", "oficina": "Director de Infraestructura", "electivo": false, "categoria": {"id": "29", "orden": 10, "nombre": "Director de Infraestructura", "requiere_declaracion_jurada": true, "nombre_corto": "Director de Infraestructura"}, "depende_de": "26", "nombre": "Director de Infraestructura"}}, {"decreto_pdf": "", "decreto_nro": null, "fecha_inicio": "", "fecha_fin": "", "id": "30", "funcionario": {"edad": 0, "foto": {"original": "https://goo.gl/7k97nP", "thumbnail_32x32": "https://goo.gl/7k97nP", "thumbnail": "https://goo.gl/7k97nP"}, "apellido": "", "url": "", "uniqueid": "", "nombrepublico": "Ing. Mauricio Di Febo", "nombre": "Ing. Mauricio Di Febo", "franjaetaria": "", "genero": "M"}, "cargo": {"superioresids": [], "id": "30", "oficina": "Coordinador de Obras de Infraestructura", "electivo": false, "categoria": {"id": "30", "orden": 10, "nombre": "Coordinador de Obras de Infraestructura", "requiere_declaracion_jurada": true, "nombre_corto": "Coordinador de Obras de Infraestructura"}, "depende_de": "29", "nombre": "Coordinador de Obras de Infraestructura"}}, {"decreto_pdf": "", "decreto_nro": null, "fecha_inicio": "", "fecha_fin": "", "id": "31", "funcionario": {"edad": 0, "foto": {"original": "https://goo.gl/7k97nP", "thumbnail_32x32": "https://goo.gl/7k97nP", "thumbnail": "https://goo.gl/7k97nP"}, "apellido": "", "url": "", "uniqueid": "", "nombrepublico": "Ing. Marina Crescimbeni", "nombre": "Ing. Marina Crescimbeni", "franjaetaria": "", "genero": "F"}, "cargo": {"superioresids": [], "id": "31", "oficina": "Coordinadora de Asuntos Ambientales", "electivo": false, "categoria": {"id": "31", "orden": 10, "nombre": "Coordinadora de Asuntos Ambientales", "requiere_declaracion_jurada": true, "nombre_corto": "Coordinadora de Asuntos Ambientales"}, "depende_de": "28", "nombre": "Coordinadora de Asuntos Ambientales"}}, {"decreto_pdf": "", "decreto_nro": null, "fecha_inicio": "", "fecha_fin": "", "id": "32", "funcionario": {"edad": 0, "foto": {"original": "https://goo.gl/7k97nP", "thumbnail_32x32": "https://goo.gl/7k97nP", "thumbnail": "https://goo.gl/7k97nP"}, "apellido": "", "url": "", "uniqueid": "", "nombrepublico": "Ing. Mariana Guardia", "nombre": "Ing. Mariana Guardia", "franjaetaria": "", "genero": "F"}, "cargo": {"superioresids": [], "id": "32", "oficina": "Coordinadora de Saneamiento", "electivo": false, "categoria": {"id": "32", "orden": 10, "nombre": "Coordinadora de Saneamiento", "requiere_declaracion_jurada": true, "nombre_corto": "Coordinadora de Saneamiento"}, "depende_de": "28", "nombre": "Coordinadora de Saneamiento"}}, {"decreto_pdf": "", "decreto_nro": null, "fecha_inicio": "", "fecha_fin": "", "id": "33", "funcionario": {"edad": 0, "foto": {"original": "https://goo.gl/7k97nP", "thumbnail_32x32": "https://goo.gl/7k97nP", "thumbnail": "https://goo.gl/7k97nP"}, "apellido": "", "url": "", "uniqueid": "", "nombrepublico": "Daniel Climaco", "nombre": "Daniel Climaco", "franjaetaria": "", "genero": "M"}, "cargo": {"superioresids": [], "id": "33", "oficina": "Director del Espacio P\u00fablico", "electivo": false, "categoria": {"id": "33", "orden": 10, "nombre": "Director del Espacio P\u00fablico", "requiere_declaracion_jurada": true, "nombre_corto": "Director del Espacio P\u00fablico"}, "depende_de": "26", "nombre": "Director del Espacio P\u00fablico"}}, {"decreto_pdf": "", "decreto_nro": null, "fecha_inicio": "", "fecha_fin": "", "id": "34", "funcionario": {"edad": 0, "foto": {"original": "https://goo.gl/7k97nP", "thumbnail_32x32": "https://goo.gl/7k97nP", "thumbnail": "https://goo.gl/7k97nP"}, "apellido": "", "url": "", "uniqueid": "", "nombrepublico": "Arq. Mar\u00eda Laura Gonz\u00e1lez", "nombre": "Arq. Mar\u00eda Laura Gonz\u00e1lez", "franjaetaria": "", "genero": "F"}, "cargo": {"superioresids": [], "id": "34", "oficina": "Directora de Obras Privadas", "electivo": false, "categoria": {"id": "34", "orden": 10, "nombre": "Directora de Obras Privadas", "requiere_declaracion_jurada": true, "nombre_corto": "Directora de Obras Privadas"}, "depende_de": "26", "nombre": "Directora de Obras Privadas"}}, {"decreto_pdf": "", "decreto_nro": null, "fecha_inicio": "", "fecha_fin": "", "id": "35", "funcionario": {"edad": 0, "foto": {"original": "https://goo.gl/7k97nP", "thumbnail_32x32": "https://goo.gl/7k97nP", "thumbnail": "https://goo.gl/7k97nP"}, "apellido": "", "url": "", "uniqueid": "", "nombrepublico": "Mario Fernando Chidichimo", "nombre": "Mario Fernando Chidichimo", "franjaetaria": "", "genero": "M"}, "cargo": {"superioresids": [], "id": "35", "oficina": "Director de Servicios de Corral\u00f3n Municipal", "electivo": false, "categoria": {"id": "35", "orden": 10, "nombre": "Director de Servicios de Corral\u00f3n Municipal", "requiere_declaracion_jurada": true, "nombre_corto": "Director de Servicios de Corral\u00f3n Municipal"}, "depende_de": "26", "nombre": "Director de Servicios de Corral\u00f3n Municipal"}}, {"decreto_pdf": "", "decreto_nro": null, "fecha_inicio": "", "fecha_fin": "", "id": "36", "funcionario": {"edad": 0, "foto": {"original": "https://goo.gl/7k97nP", "thumbnail_32x32": "https://goo.gl/7k97nP", "thumbnail": "https://goo.gl/7k97nP"}, "apellido": "", "url": "", "uniqueid": "", "nombrepublico": "Cr. Guillermo Gonz\u00e1lez", "nombre": "Cr. Guillermo Gonz\u00e1lez", "franjaetaria": "", "genero": "M"}, "cargo": {"superioresids": [], "id": "36", "oficina": "Subcoordinador de Administraci\u00f3n del Corral\u00f3n Municipal", "electivo": false, "categoria": {"id": "36", "orden": 10, "nombre": "Subcoordinador de Administraci\u00f3n del Corral\u00f3n Municipal", "requiere_declaracion_jurada": true, "nombre_corto": "Subcoordinador de Administraci\u00f3n del Corral\u00f3n Municipal"}, "depende_de": "35", "nombre": "Subcoordinador de Administraci\u00f3n del Corral\u00f3n Municipal"}}, {"decreto_pdf": "", "decreto_nro": null, "fecha_inicio": "", "fecha_fin": "", "id": "37", "funcionario": {"edad": 0, "foto": {"original": "https://goo.gl/7k97nP", "thumbnail_32x32": "https://goo.gl/7k97nP", "thumbnail": "https://goo.gl/7k97nP"}, "apellido": "", "url": "", "uniqueid": "", "nombrepublico": "Gabriel D\u00edaz", "nombre": "Gabriel D\u00edaz", "franjaetaria": "", "genero": "M"}, "cargo": {"superioresids": [], "id": "37", "oficina": "Coordinador de Log\u00edstica y Operativa de los Servicios P\u00fablicos", "electivo": false, "categoria": {"id": "37", "orden": 10, "nombre": "Coordinador de Log\u00edstica y Operativa de los Servicios P\u00fablicos", "requiere_declaracion_jurada": true, "nombre_corto": "Coordinador de Log\u00edstica y Operativa de los Servicios P\u00fablicos"}, "depende_de": "26", "nombre": "Coordinador de Log\u00edstica y Operativa de los Servicios P\u00fablicos"}}, {"decreto_pdf": "", "decreto_nro": null, "fecha_inicio": "", "fecha_fin": "", "id": "38", "funcionario": {"edad": 0, "foto": {"original": "https://goo.gl/7k97nP", "thumbnail_32x32": "https://goo.gl/7k97nP", "thumbnail": "https://goo.gl/7k97nP"}, "apellido": "", "url": "", "uniqueid": "", "nombrepublico": "Jorge Mulinetti", "nombre": "Jorge Mulinetti", "franjaetaria": "", "genero": "M"}, "cargo": {"superioresids": [], "id": "38", "oficina": "Coordinador de Electricidad y Alumbrado", "electivo": false, "categoria": {"id": "38", "orden": 10, "nombre": "Coordinador de Electricidad y Alumbrado", "requiere_declaracion_jurada": true, "nombre_corto": "Coordinador de Electricidad y Alumbrado"}, "depende_de": "26", "nombre": "Coordinador de Electricidad y Alumbrado"}}, {"decreto_pdf": "", "decreto_nro": null, "fecha_inicio": "", "fecha_fin": "", "id": "39", "funcionario": {"edad": 0, "foto": {"original": "https://goo.gl/7k97nP", "thumbnail_32x32": "https://goo.gl/7k97nP", "thumbnail": "https://goo.gl/7k97nP"}, "apellido": "", "url": "", "uniqueid": "", "nombrepublico": "Arq. Pablo Gonz\u00e1lez", "nombre": "Arq. Pablo Gonz\u00e1lez", "franjaetaria": "", "genero": "M"}, "cargo": {"superioresids": [], "id": "39", "oficina": "Presidente del Instituto Municipal de la Vivienda e Infraestructura Habitacional", "electivo": false, "categoria": {"id": "39", "orden": 10, "nombre": "Presidente del Instituto Municipal de la Vivienda e Infraestructura Habitacional", "requiere_declaracion_jurada": true, "nombre_corto": "Presidente del Instituto Municipal de la Vivienda e Infraestructura Habitacional"}, "depende_de": "4", "nombre": "Presidente del Instituto Municipal de la Vivienda e Infraestructura Habitacional"}}, {"decreto_pdf": "", "decreto_nro": null, "fecha_inicio": "", "fecha_fin": "", "id": "40", "funcionario": {"edad": 0, "foto": {"original": "https://goo.gl/7k97nP", "thumbnail_32x32": "https://goo.gl/7k97nP", "thumbnail": "https://goo.gl/7k97nP"}, "apellido": "", "url": "", "uniqueid": "", "nombrepublico": "Silvia Cuello", "nombre": "Silvia Cuello", "franjaetaria": "", "genero": "F"}, "cargo": {"superioresids": [], "id": "40", "oficina": "Vicepresidenta del Instituto Municipal de la Vivienda e Infraestructura Habitacional", "electivo": false, "categoria": {"id": "40", "orden": 10, "nombre": "Vicepresidenta del Instituto Municipal de la Vivienda e Infraestructura Habitacional", "requiere_declaracion_jurada": true, "nombre_corto": "Vicepresidenta del Instituto Municipal de la Vivienda e Infraestructura Habitacional"}, "depende_de": "4", "nombre": "Vicepresidenta del Instituto Municipal de la Vivienda e Infraestructura Habitacional"}}, {"decreto_pdf": "", "decreto_nro": null, "fecha_inicio": "", "fecha_fin": "", "id": "41", "funcionario": {"edad": 0, "foto": {"original": "https://goo.gl/7k97nP", "thumbnail_32x32": "https://goo.gl/7k97nP", "thumbnail": "https://goo.gl/7k97nP"}, "apellido": "", "url": "", "uniqueid": "", "nombrepublico": "Hugo Fern\u00e1ndez", "nombre": "Hugo Fern\u00e1ndez", "franjaetaria": "", "genero": "M"}, "cargo": {"superioresids": [], "id": "41", "oficina": "Director de Administraci\u00f3n del Instituto Municipal de la Vivienda e Infraestructura Habitacional", "electivo": false, "categoria": {"id": "41", "orden": 10, "nombre": "Director de Administraci\u00f3n del Instituto Municipal de la Vivienda e Infraestructura Habitacional", "requiere_declaracion_jurada": true, "nombre_corto": "Director de Administraci\u00f3n del Instituto Municipal de la Vivienda e Infraestructura Habitacional"}, "depende_de": "4", "nombre": "Director de Administraci\u00f3n del Instituto Municipal de la Vivienda e Infraestructura Habitacional"}}, {"decreto_pdf": "", "decreto_nro": null, "fecha_inicio": "", "fecha_fin": "", "id": "42", "funcionario": {"edad": 0, "foto": {"original": "https://goo.gl/7k97nP", "thumbnail_32x32": "https://goo.gl/7k97nP", "thumbnail": "https://goo.gl/7k97nP"}, "apellido": "", "url": "", "uniqueid": "", "nombrepublico": "Lic. Hercilia Brusasca", "nombre": "Lic. Hercilia Brusasca", "franjaetaria": "", "genero": "F"}, "cargo": {"superioresids": [], "id": "42", "oficina": "Directora de Pol\u00edticas Sociales y Habitacionales", "electivo": false, "categoria": {"id": "42", "orden": 10, "nombre": "Directora de Pol\u00edticas Sociales y Habitacionales", "requiere_declaracion_jurada": true, "nombre_corto": "Directora de Pol\u00edticas Sociales y Habitacionales"}, "depende_de": "4", "nombre": "Directora de Pol\u00edticas Sociales y Habitacionales"}}, {"decreto_pdf": "", "decreto_nro": null, "fecha_inicio": "", "fecha_fin": "", "id": "43", "funcionario": {"edad": 0, "foto": {"original": "https://goo.gl/7k97nP", "thumbnail_32x32": "https://goo.gl/7k97nP", "thumbnail": "https://goo.gl/7k97nP"}, "apellido": "", "url": "", "uniqueid": "", "nombrepublico": "Abog. Danilo Baiocchi", "nombre": "Abog. Danilo Baiocchi", "franjaetaria": "", "genero": "M"}, "cargo": {"superioresids": [], "id": "43", "oficina": "Vicepresidente Instituto Municipal de inversi\u00f3n", "electivo": false, "categoria": {"id": "43", "orden": 10, "nombre": "Vicepresidente Instituto Municipal de inversi\u00f3n", "requiere_declaracion_jurada": true, "nombre_corto": "Vicepresidente Instituto Municipal de inversi\u00f3n"}, "depende_de": "4", "nombre": "Vicepresidente Instituto Municipal de inversi\u00f3n"}}, {"decreto_pdf": "", "decreto_nro": null, "fecha_inicio": "", "fecha_fin": "", "id": "44", "funcionario": {"edad": 0, "foto": {"original": "https://goo.gl/7k97nP", "thumbnail_32x32": "https://goo.gl/7k97nP", "thumbnail": "https://goo.gl/7k97nP"}, "apellido": "", "url": "", "uniqueid": "", "nombrepublico": "Abog. Oscar Barroso", "nombre": "Abog. Oscar Barroso", "franjaetaria": "", "genero": "M"}, "cargo": {"superioresids": [], "id": "44", "oficina": "Asesor Letrado", "electivo": false, "categoria": {"id": "44", "orden": 10, "nombre": "Asesor Letrado", "requiere_declaracion_jurada": true, "nombre_corto": "Asesor Letrado"}, "depende_de": "1", "nombre": "Asesor Letrado"}}, {"decreto_pdf": "", "decreto_nro": null, "fecha_inicio": "", "fecha_fin": "", "id": "45", "funcionario": {"edad": 0, "foto": {"original": "https://goo.gl/7k97nP", "thumbnail_32x32": "https://goo.gl/7k97nP", "thumbnail": "https://goo.gl/7k97nP"}, "apellido": "", "url": "", "uniqueid": "", "nombrepublico": "Abog. Ricardo Borsatto", "nombre": "Abog. Ricardo Borsatto", "franjaetaria": "", "genero": "M"}, "cargo": {"superioresids": [], "id": "45", "oficina": "Coordinador de Legal y T\u00e9cnica", "electivo": false, "categoria": {"id": "45", "orden": 10, "nombre": "Coordinador de Legal y T\u00e9cnica", "requiere_declaracion_jurada": true, "nombre_corto": "Coordinador de Legal y T\u00e9cnica"}, "depende_de": "44", "nombre": "Coordinador de Legal y T\u00e9cnica"}}, {"decreto_pdf": "", "decreto_nro": null, "fecha_inicio": "", "fecha_fin": "", "id": "46", "funcionario": {"edad": 0, "foto": {"original": "https://goo.gl/7k97nP", "thumbnail_32x32": "https://goo.gl/7k97nP", "thumbnail": "https://goo.gl/7k97nP"}, "apellido": "", "url": "", "uniqueid": "", "nombrepublico": "Abog. Fernanda Gabriela Bertea", "nombre": "Abog. Fernanda Gabriela Bertea", "franjaetaria": "", "genero": "F"}, "cargo": {"superioresids": [], "id": "46", "oficina": "Coordinadora de Admisiones, Concursos y Sumarios", "electivo": false, "categoria": {"id": "46", "orden": 10, "nombre": "Coordinadora de Admisiones, Concursos y Sumarios", "requiere_declaracion_jurada": true, "nombre_corto": "Coordinadora de Admisiones, Concursos y Sumarios"}, "depende_de": "44", "nombre": "Coordinadora de Admisiones, Concursos y Sumarios"}}, {"decreto_pdf": "", "decreto_nro": null, "fecha_inicio": "", "fecha_fin": "", "id": "47", "funcionario": {"edad": 0, "foto": {"original": "https://goo.gl/7k97nP", "thumbnail_32x32": "https://goo.gl/7k97nP", "thumbnail": "https://goo.gl/7k97nP"}, "apellido": "", "url": "", "uniqueid": "", "nombrepublico": "Dr. Humberto Jure", "nombre": "Dr. Humberto Jure", "franjaetaria": "", "genero": "M"}, "cargo": {"superioresids": [], "id": "47", "oficina": "Secretario de Salud", "electivo": false, "categoria": {"id": "47", "orden": 10, "nombre": "Secretario de Salud", "requiere_declaracion_jurada": true, "nombre_corto": "Secretario de Salud"}, "depende_de": "1", "nombre": "Secretario de Salud"}}, {"decreto_pdf": "", "decreto_nro": null, "fecha_inicio": "", "fecha_fin": "", "id": "48", "funcionario": {"edad": 0, "foto": {"original": "https://goo.gl/7k97nP", "thumbnail_32x32": "https://goo.gl/7k97nP", "thumbnail": "https://goo.gl/7k97nP"}, "apellido": "", "url": "", "uniqueid": "", "nombrepublico": "Dra. Raquel Rodrigo", "nombre": "Dra. Raquel Rodrigo", "franjaetaria": "", "genero": "F"}, "cargo": {"superioresids": [], "id": "48", "oficina": "Subsecretaria de Salud", "electivo": false, "categoria": {"id": "48", "orden": 10, "nombre": "Subsecretaria de Salud", "requiere_declaracion_jurada": true, "nombre_corto": "Subsecretaria de Salud"}, "depende_de": "47", "nombre": "Subsecretaria de Salud"}}, {"decreto_pdf": "", "decreto_nro": null, "fecha_inicio": "", "fecha_fin": "", "id": "49", "funcionario": {"edad": 0, "foto": {"original": "https://goo.gl/7k97nP", "thumbnail_32x32": "https://goo.gl/7k97nP", "thumbnail": "https://goo.gl/7k97nP"}, "apellido": "", "url": "", "uniqueid": "", "nombrepublico": "Lic. Rosana Tuninetti", "nombre": "Lic. Rosana Tuninetti", "franjaetaria": "", "genero": "F"}, "cargo": {"superioresids": [], "id": "49", "oficina": "Directora de los Centros de Atenci\u00f3n Primaria de la Salud Municipal (CAPS)", "electivo": false, "categoria": {"id": "49", "orden": 10, "nombre": "Directora de los Centros de Atenci\u00f3n Primaria de la Salud Municipal (CAPS)", "requiere_declaracion_jurada": true, "nombre_corto": "Directora de los Centros de Atenci\u00f3n Primaria de la Salud Municipal (CAPS)"}, "depende_de": "48", "nombre": "Directora de los Centros de Atenci\u00f3n Primaria de la Salud Municipal (CAPS)"}}, {"decreto_pdf": "", "decreto_nro": null, "fecha_inicio": "", "fecha_fin": "", "id": "50", "funcionario": {"edad": 0, "foto": {"original": "https://goo.gl/7k97nP", "thumbnail_32x32": "https://goo.gl/7k97nP", "thumbnail": "https://goo.gl/7k97nP"}, "apellido": "", "url": "", "uniqueid": "", "nombrepublico": "Dr. Ra\u00fal Marchegiani", "nombre": "Dr. Ra\u00fal Marchegiani", "franjaetaria": "", "genero": "M"}, "cargo": {"superioresids": [], "id": "50", "oficina": "Director de la Asistencia P\u00fablica", "electivo": false, "categoria": {"id": "50", "orden": 10, "nombre": "Director de la Asistencia P\u00fablica", "requiere_declaracion_jurada": true, "nombre_corto": "Director de la Asistencia P\u00fablica"}, "depende_de": "48", "nombre": "Director de la Asistencia P\u00fablica"}}, {"decreto_pdf": "", "decreto_nro": null, "fecha_inicio": "", "fecha_fin": "", "id": "51", "funcionario": {"edad": 0, "foto": {"original": "https://goo.gl/7k97nP", "thumbnail_32x32": "https://goo.gl/7k97nP", "thumbnail": "https://goo.gl/7k97nP"}, "apellido": "", "url": "", "uniqueid": "", "nombrepublico": "Lic. Alejandra \u00c1lvarez", "nombre": "Lic. Alejandra \u00c1lvarez", "franjaetaria": "", "genero": "F"}, "cargo": {"superioresids": [], "id": "51", "oficina": "Directora administrativa del Hogar para la Sana Estad\u00eda \"Roberto Velo de \u00cdpola\"", "electivo": false, "categoria": {"id": "51", "orden": 10, "nombre": "Directora administrativa del Hogar para la Sana Estad\u00eda \"Roberto Velo de \u00cdpola\"", "requiere_declaracion_jurada": true, "nombre_corto": "Directora administrativa del Hogar para la Sana Estad\u00eda \"Roberto Velo de \u00cdpola\""}, "depende_de": "48", "nombre": "Directora administrativa del Hogar para la Sana Estad\u00eda \"Roberto Velo de \u00cdpola\""}}, {"decreto_pdf": "", "decreto_nro": null, "fecha_inicio": "", "fecha_fin": "", "id": "52", "funcionario": {"edad": 0, "foto": {"original": "https://goo.gl/7k97nP", "thumbnail_32x32": "https://goo.gl/7k97nP", "thumbnail": "https://goo.gl/7k97nP"}, "apellido": "", "url": "", "uniqueid": "", "nombrepublico": "Carlina Gudi\u00f1o", "nombre": "Carlina Gudi\u00f1o", "franjaetaria": "", "genero": "F"}, "cargo": {"superioresids": [], "id": "52", "oficina": "Directora de Salud del Hogar para la Santa Estad\u00eda \"Roberto Velo de \u00cdpola\"", "electivo": false, "categoria": {"id": "52", "orden": 10, "nombre": "Directora de Salud del Hogar para la Santa Estad\u00eda \"Roberto Velo de \u00cdpola\"", "requiere_declaracion_jurada": true, "nombre_corto": "Directora de Salud del Hogar para la Santa Estad\u00eda \"Roberto Velo de \u00cdpola\""}, "depende_de": "48", "nombre": "Directora de Salud del Hogar para la Santa Estad\u00eda \"Roberto Velo de \u00cdpola\""}}, {"decreto_pdf": "", "decreto_nro": null, "fecha_inicio": "", "fecha_fin": "", "id": "53", "funcionario": {"edad": 0, "foto": {"original": "https://goo.gl/7k97nP", "thumbnail_32x32": "https://goo.gl/7k97nP", "thumbnail": "https://goo.gl/7k97nP"}, "apellido": "", "url": "", "uniqueid": "", "nombrepublico": "Claudia Fabiana Arias", "nombre": "Claudia Fabiana Arias", "franjaetaria": "", "genero": "F"}, "cargo": {"superioresids": [], "id": "53", "oficina": "Secretaria de Inclusi\u00f3n Social y Familia", "electivo": false, "categoria": {"id": "53", "orden": 10, "nombre": "Secretaria de Inclusi\u00f3n Social y Familia", "requiere_declaracion_jurada": true, "nombre_corto": "Secretaria de Inclusi\u00f3n Social y Familia"}, "depende_de": "1", "nombre": "Secretaria de Inclusi\u00f3n Social y Familia"}}, {"decreto_pdf": "", "decreto_nro": null, "fecha_inicio": "", "fecha_fin": "", "id": "54", "funcionario": {"edad": 0, "foto": {"original": "https://goo.gl/7k97nP", "thumbnail_32x32": "https://goo.gl/7k97nP", "thumbnail": "https://goo.gl/7k97nP"}, "apellido": "", "url": "", "uniqueid": "", "nombrepublico": "Prof. Jorge Arg\u00fcello", "nombre": "Prof. Jorge Arg\u00fcello", "franjaetaria": "", "genero": "M"}, "cargo": {"superioresids": [], "id": "54", "oficina": "Subsecretario de Inclusi\u00f3n Social", "electivo": false, "categoria": {"id": "54", "orden": 10, "nombre": "Subsecretario de Inclusi\u00f3n Social", "requiere_declaracion_jurada": true, "nombre_corto": "Subsecretario de Inclusi\u00f3n Social"}, "depende_de": "53", "nombre": "Subsecretario de Inclusi\u00f3n Social"}}, {"decreto_pdf": "", "decreto_nro": null, "fecha_inicio": "", "fecha_fin": "", "id": "55", "funcionario": {"edad": 0, "foto": {"original": "https://goo.gl/7k97nP", "thumbnail_32x32": "https://goo.gl/7k97nP", "thumbnail": "https://goo.gl/7k97nP"}, "apellido": "", "url": "", "uniqueid": "", "nombrepublico": "Lic. Mar\u00eda Emilia Calder\u00f3n", "nombre": "Lic. Mar\u00eda Emilia Calder\u00f3n", "franjaetaria": "", "genero": "F"}, "cargo": {"superioresids": [], "id": "55", "oficina": "Coordinadora de Familia", "electivo": false, "categoria": {"id": "55", "orden": 10, "nombre": "Coordinadora de Familia", "requiere_declaracion_jurada": true, "nombre_corto": "Coordinadora de Familia"}, "depende_de": "54", "nombre": "Coordinadora de Familia"}}, {"decreto_pdf": "", "decreto_nro": null, "fecha_inicio": "", "fecha_fin": "", "id": "56", "funcionario": {"edad": 0, "foto": {"original": "https://goo.gl/7k97nP", "thumbnail_32x32": "https://goo.gl/7k97nP", "thumbnail": "https://goo.gl/7k97nP"}, "apellido": "", "url": "", "uniqueid": "", "nombrepublico": "Lic. Mar\u00eda Virginia Mart\u00ed", "nombre": "Lic. Mar\u00eda Virginia Mart\u00ed", "franjaetaria": "", "genero": "F"}, "cargo": {"superioresids": [], "id": "56", "oficina": "Coordinadora de Econom\u00eda Social y Solidaria", "electivo": false, "categoria": {"id": "56", "orden": 10, "nombre": "Coordinadora de Econom\u00eda Social y Solidaria", "requiere_declaracion_jurada": true, "nombre_corto": "Coordinadora de Econom\u00eda Social y Solidaria"}, "depende_de": "54", "nombre": "Coordinadora de Econom\u00eda Social y Solidaria"}}, {"decreto_pdf": "", "decreto_nro": null, "fecha_inicio": "", "fecha_fin": "", "id": "57", "funcionario": {"edad": 0, "foto": {"original": "https://goo.gl/7k97nP", "thumbnail_32x32": "https://goo.gl/7k97nP", "thumbnail": "https://goo.gl/7k97nP"}, "apellido": "", "url": "", "uniqueid": "", "nombrepublico": "Dr. Julio Tabares", "nombre": "Dr. Julio Tabares", "franjaetaria": "", "genero": "M"}, "cargo": {"superioresids": [], "id": "57", "oficina": "Subsecretario de Desarrollo Humano", "electivo": false, "categoria": {"id": "57", "orden": 10, "nombre": "Subsecretario de Desarrollo Humano", "requiere_declaracion_jurada": true, "nombre_corto": "Subsecretario de Desarrollo Humano"}, "depende_de": "53", "nombre": "Subsecretario de Desarrollo Humano"}}, {"decreto_pdf": "", "decreto_nro": null, "fecha_inicio": "", "fecha_fin": "", "id": "58", "funcionario": {"edad": 0, "foto": {"original": "https://goo.gl/7k97nP", "thumbnail_32x32": "https://goo.gl/7k97nP", "thumbnail": "https://goo.gl/7k97nP"}, "apellido": "", "url": "", "uniqueid": "", "nombrepublico": "Ver\u00f3nica Chavero", "nombre": "Ver\u00f3nica Chavero", "franjaetaria": "", "genero": "F"}, "cargo": {"superioresids": [], "id": "58", "oficina": "Directora de Discapacidad", "electivo": false, "categoria": {"id": "58", "orden": 10, "nombre": "Directora de Discapacidad", "requiere_declaracion_jurada": true, "nombre_corto": "Directora de Discapacidad"}, "depende_de": "57", "nombre": "Directora de Discapacidad"}}, {"decreto_pdf": "", "decreto_nro": null, "fecha_inicio": "", "fecha_fin": "", "id": "59", "funcionario": {"edad": 0, "foto": {"original": "https://goo.gl/7k97nP", "thumbnail_32x32": "https://goo.gl/7k97nP", "thumbnail": "https://goo.gl/7k97nP"}, "apellido": "", "url": "", "uniqueid": "", "nombrepublico": "Daniel Massara", "nombre": "Daniel Massara", "franjaetaria": "", "genero": "M"}, "cargo": {"superioresids": [], "id": "59", "oficina": "Coordinadora de Derechos Humanos, Diversidad y G\u00e9nero", "electivo": false, "categoria": {"id": "59", "orden": 10, "nombre": "Coordinadora de Derechos Humanos, Diversidad y G\u00e9nero", "requiere_declaracion_jurada": true, "nombre_corto": "Coordinadora de Derechos Humanos, Diversidad y G\u00e9nero"}, "depende_de": "57", "nombre": "Coordinadora de Derechos Humanos, Diversidad y G\u00e9nero"}}, {"decreto_pdf": "", "decreto_nro": null, "fecha_inicio": "", "fecha_fin": "", "id": "60", "funcionario": {"edad": 0, "foto": {"original": "https://goo.gl/7k97nP", "thumbnail_32x32": "https://goo.gl/7k97nP", "thumbnail": "https://goo.gl/7k97nP"}, "apellido": "", "url": "", "uniqueid": "", "nombrepublico": "Melina Mosquera D\u00edaz", "nombre": "Melina Mosquera D\u00edaz", "franjaetaria": "", "genero": "F"}, "cargo": {"superioresids": [], "id": "60", "oficina": "Directora de Escuela Granja \"Los Amigos\"", "electivo": false, "categoria": {"id": "60", "orden": 10, "nombre": "Directora de Escuela Granja \"Los Amigos\"", "requiere_declaracion_jurada": true, "nombre_corto": "Directora de Escuela Granja \"Los Amigos\""}, "depende_de": "53", "nombre": "Directora de Escuela Granja \"Los Amigos\""}}, {"decreto_pdf": "", "decreto_nro": null, "fecha_inicio": "", "fecha_fin": "", "id": "61", "funcionario": {"edad": 0, "foto": {"original": "https://goo.gl/7k97nP", "thumbnail_32x32": "https://goo.gl/7k97nP", "thumbnail": "https://goo.gl/7k97nP"}, "apellido": "", "url": "", "uniqueid": "", "nombrepublico": "Prof. Rafael Sachetto", "nombre": "Prof. Rafael Sachetto", "franjaetaria": "", "genero": "M"}, "cargo": {"superioresids": [], "id": "61", "oficina": "Secretario de Gobierno y V\u00ednculos Comunitarios", "electivo": false, "categoria": {"id": "61", "orden": 10, "nombre": "Secretario de Gobierno y V\u00ednculos Comunitarios", "requiere_declaracion_jurada": true, "nombre_corto": "Secretario de Gobierno y V\u00ednculos Comunitarios"}, "depende_de": "1", "nombre": "Secretario de Gobierno y V\u00ednculos Comunitarios"}}, {"decreto_pdf": "", "decreto_nro": null, "fecha_inicio": "", "fecha_fin": "", "id": "62", "funcionario": {"edad": 0, "foto": {"original": "https://goo.gl/7k97nP", "thumbnail_32x32": "https://goo.gl/7k97nP", "thumbnail": "https://goo.gl/7k97nP"}, "apellido": "", "url": "", "uniqueid": "", "nombrepublico": "Mar\u00eda Valeria Su\u00e1rez", "nombre": "Mar\u00eda Valeria Su\u00e1rez", "franjaetaria": "", "genero": "F"}, "cargo": {"superioresids": [], "id": "62", "oficina": "Subsecretaria de Inspecci\u00f3n General", "electivo": false, "categoria": {"id": "62", "orden": 10, "nombre": "Subsecretaria de Inspecci\u00f3n General", "requiere_declaracion_jurada": true, "nombre_corto": "Subsecretaria de Inspecci\u00f3n General"}, "depende_de": "61", "nombre": "Subsecretaria de Inspecci\u00f3n General"}}, {"decreto_pdf": "", "decreto_nro": null, "fecha_inicio": "", "fecha_fin": "", "id": "63", "funcionario": {"edad": 0, "foto": {"original": "https://goo.gl/7k97nP", "thumbnail_32x32": "https://goo.gl/7k97nP", "thumbnail": "https://goo.gl/7k97nP"}, "apellido": "", "url": "", "uniqueid": "", "nombrepublico": "M\u00e9d. Veterinario Federico Soria", "nombre": "M\u00e9d. Veterinario Federico Soria", "franjaetaria": "", "genero": "M"}, "cargo": {"superioresids": [], "id": "63", "oficina": "Director de Salud Animal y Control de Zoonosis", "electivo": false, "categoria": {"id": "63", "orden": 10, "nombre": "Director de Salud Animal y Control de Zoonosis", "requiere_declaracion_jurada": true, "nombre_corto": "Director de Salud Animal y Control de Zoonosis"}, "depende_de": "62", "nombre": "Director de Salud Animal y Control de Zoonosis"}}, {"decreto_pdf": "", "decreto_nro": null, "fecha_inicio": "", "fecha_fin": "", "id": "64", "funcionario": {"edad": 0, "foto": {"original": "https://goo.gl/7k97nP", "thumbnail_32x32": "https://goo.gl/7k97nP", "thumbnail": "https://goo.gl/7k97nP"}, "apellido": "", "url": "", "uniqueid": "", "nombrepublico": "Lic. Gabriela Redondo", "nombre": "Lic. Gabriela Redondo", "franjaetaria": "", "genero": "M"}, "cargo": {"superioresids": [], "id": "64", "oficina": "Subsecretaria de Cultura", "electivo": false, "categoria": {"id": "64", "orden": 10, "nombre": "Subsecretaria de Cultura", "requiere_declaracion_jurada": true, "nombre_corto": "Subsecretaria de Cultura"}, "depende_de": "61", "nombre": "Subsecretaria de Cultura"}}, {"decreto_pdf": "", "decreto_nro": null, "fecha_inicio": "", "fecha_fin": "", "id": "65", "funcionario": {"edad": 0, "foto": {"original": "https://goo.gl/7k97nP", "thumbnail_32x32": "https://goo.gl/7k97nP", "thumbnail": "https://goo.gl/7k97nP"}, "apellido": "", "url": "", "uniqueid": "", "nombrepublico": "Lic. Laura Giordanino", "nombre": "Lic. Laura Giordanino", "franjaetaria": "", "genero": "F"}, "cargo": {"superioresids": [], "id": "65", "oficina": "Coordinador del Centro Cultural Comunitario \"Leonardo Favio\"", "electivo": false, "categoria": {"id": "65", "orden": 10, "nombre": "Coordinador del Centro Cultural Comunitario \"Leonardo Favio\"", "requiere_declaracion_jurada": true, "nombre_corto": "Coordinador del Centro Cultural Comunitario \"Leonardo Favio\""}, "depende_de": "64", "nombre": "Coordinador del Centro Cultural Comunitario \"Leonardo Favio\""}}, {"decreto_pdf": "", "decreto_nro": null, "fecha_inicio": "", "fecha_fin": "", "id": "66", "funcionario": {"edad": 0, "foto": {"original": "https://goo.gl/7k97nP", "thumbnail_32x32": "https://goo.gl/7k97nP", "thumbnail": "https://goo.gl/7k97nP"}, "apellido": "", "url": "", "uniqueid": "", "nombrepublico": "Arq. Hugo Las Heras", "nombre": "Arq. Hugo Las Heras", "franjaetaria": "", "genero": "M"}, "cargo": {"superioresids": [], "id": "66", "oficina": "Director de Patrimonio Hist\u00f3rico", "electivo": false, "categoria": {"id": "66", "orden": 10, "nombre": "Director de Patrimonio Hist\u00f3rico", "requiere_declaracion_jurada": true, "nombre_corto": "Director de Patrimonio Hist\u00f3rico"}, "depende_de": "64", "nombre": "Director de Patrimonio Hist\u00f3rico"}}, {"decreto_pdf": "", "decreto_nro": null, "fecha_inicio": "", "fecha_fin": "", "id": "67", "funcionario": {"edad": 0, "foto": {"original": "https://goo.gl/7k97nP", "thumbnail_32x32": "https://goo.gl/7k97nP", "thumbnail": "https://goo.gl/7k97nP"}, "apellido": "", "url": "", "uniqueid": "", "nombrepublico": "Prof. Anal\u00eda del Carmen Godoy", "nombre": "Prof. Anal\u00eda del Carmen Godoy", "franjaetaria": "", "genero": "F"}, "cargo": {"superioresids": [], "id": "67", "oficina": "Directora de Museos", "electivo": false, "categoria": {"id": "67", "orden": 10, "nombre": "Directora de Museos", "requiere_declaracion_jurada": true, "nombre_corto": "Directora de Museos"}, "depende_de": "64", "nombre": "Directora de Museos"}}, {"decreto_pdf": "", "decreto_nro": null, "fecha_inicio": "", "fecha_fin": "", "id": "68", "funcionario": {"edad": 0, "foto": {"original": "https://goo.gl/7k97nP", "thumbnail_32x32": "https://goo.gl/7k97nP", "thumbnail": "https://goo.gl/7k97nP"}, "apellido": "", "url": "", "uniqueid": "", "nombrepublico": "Gabriela Cabello", "nombre": "Gabriela Cabello", "franjaetaria": "", "genero": "F"}, "cargo": {"superioresids": [], "id": "68", "oficina": "Directora de Procesos de Gesti\u00f3n Aministrativa", "electivo": false, "categoria": {"id": "68", "orden": 10, "nombre": "Directora de Procesos de Gesti\u00f3n Aministrativa", "requiere_declaracion_jurada": true, "nombre_corto": "Directora de Procesos de Gesti\u00f3n Aministrativa"}, "depende_de": "61", "nombre": "Directora de Procesos de Gesti\u00f3n Aministrativa"}}, {"decreto_pdf": "", "decreto_nro": null, "fecha_inicio": "", "fecha_fin": "", "id": "69", "funcionario": {"edad": 0, "foto": {"original": "https://goo.gl/7k97nP", "thumbnail_32x32": "https://goo.gl/7k97nP", "thumbnail": "https://goo.gl/7k97nP"}, "apellido": "", "url": "", "uniqueid": "", "nombrepublico": "Hern\u00e1n Ipp\u00f3lito", "nombre": "Hern\u00e1n Ipp\u00f3lito", "franjaetaria": "", "genero": "M"}, "cargo": {"superioresids": [], "id": "69", "oficina": "Director de V\u00ednculos Comunitarios", "electivo": false, "categoria": {"id": "69", "orden": 10, "nombre": "Director de V\u00ednculos Comunitarios", "requiere_declaracion_jurada": true, "nombre_corto": "Director de V\u00ednculos Comunitarios"}, "depende_de": "61", "nombre": "Director de V\u00ednculos Comunitarios"}}, {"decreto_pdf": "", "decreto_nro": null, "fecha_inicio": "", "fecha_fin": "", "id": "70", "funcionario": {"edad": 0, "foto": {"original": "https://goo.gl/7k97nP", "thumbnail_32x32": "https://goo.gl/7k97nP", "thumbnail": "https://goo.gl/7k97nP"}, "apellido": "", "url": "", "uniqueid": "", "nombrepublico": "Enrique Pires", "nombre": "Enrique Pires", "franjaetaria": "", "genero": "M"}, "cargo": {"superioresids": [], "id": "70", "oficina": "Director de Participaci\u00f3n Vecinal", "electivo": false, "categoria": {"id": "70", "orden": 10, "nombre": "Director de Participaci\u00f3n Vecinal", "requiere_declaracion_jurada": true, "nombre_corto": "Director de Participaci\u00f3n Vecinal"}, "depende_de": "61", "nombre": "Director de Participaci\u00f3n Vecinal"}}, {"decreto_pdf": "", "decreto_nro": null, "fecha_inicio": "", "fecha_fin": "", "id": "71", "funcionario": {"edad": 0, "foto": {"original": "https://goo.gl/7k97nP", "thumbnail_32x32": "https://goo.gl/7k97nP", "thumbnail": "https://goo.gl/7k97nP"}, "apellido": "", "url": "", "uniqueid": "", "nombrepublico": "Laura S\u00e1nchez", "nombre": "Laura S\u00e1nchez", "franjaetaria": "", "genero": "F"}, "cargo": {"superioresids": [], "id": "71", "oficina": "Subcoordinadora de Participaci\u00f3n Vecinal", "electivo": false, "categoria": {"id": "71", "orden": 10, "nombre": "Subcoordinadora de Participaci\u00f3n Vecinal", "requiere_declaracion_jurada": true, "nombre_corto": "Subcoordinadora de Participaci\u00f3n Vecinal"}, "depende_de": "70", "nombre": "Subcoordinadora de Participaci\u00f3n Vecinal"}}, {"decreto_pdf": "", "decreto_nro": null, "fecha_inicio": "", "fecha_fin": "", "id": "72", "funcionario": {"edad": 0, "foto": {"original": "https://goo.gl/7k97nP", "thumbnail_32x32": "https://goo.gl/7k97nP", "thumbnail": "https://goo.gl/7k97nP"}, "apellido": "", "url": "", "uniqueid": "", "nombrepublico": "Abog. Rodrigo Pablo Hayas", "nombre": "Abog. Rodrigo Pablo Hayas", "franjaetaria": "", "genero": "M"}, "cargo": {"superioresids": [], "id": "72", "oficina": "Director de relaciones Laborales, Capital Humano y T\u00e9nico", "electivo": false, "categoria": {"id": "72", "orden": 10, "nombre": "Director de relaciones Laborales, Capital Humano y T\u00e9nico", "requiere_declaracion_jurada": true, "nombre_corto": "Director de relaciones Laborales, Capital Humano y T\u00e9nico"}, "depende_de": "61", "nombre": "Director de relaciones Laborales, Capital Humano y T\u00e9nico"}}, {"decreto_pdf": "", "decreto_nro": null, "fecha_inicio": "", "fecha_fin": "", "id": "73", "funcionario": {"edad": 0, "foto": {"original": "https://goo.gl/7k97nP", "thumbnail_32x32": "https://goo.gl/7k97nP", "thumbnail": "https://goo.gl/7k97nP"}, "apellido": "", "url": "", "uniqueid": "", "nombrepublico": "Tec. Daniel L\u00f3pez", "nombre": "Tec. Daniel L\u00f3pez", "franjaetaria": "", "genero": "M"}, "cargo": {"superioresids": [], "id": "73", "oficina": "Jefe de Registro Civil", "electivo": false, "categoria": {"id": "73", "orden": 10, "nombre": "Jefe de Registro Civil", "requiere_declaracion_jurada": true, "nombre_corto": "Jefe de Registro Civil"}, "depende_de": "61", "nombre": "Jefe de Registro Civil"}}, {"decreto_pdf": "", "decreto_nro": null, "fecha_inicio": "", "fecha_fin": "", "id": "74", "funcionario": {"edad": 0, "foto": {"original": "https://goo.gl/7k97nP", "thumbnail_32x32": "https://goo.gl/7k97nP", "thumbnail": "https://goo.gl/7k97nP"}, "apellido": "", "url": "", "uniqueid": "", "nombrepublico": "Carlos Vivas", "nombre": "Carlos Vivas", "franjaetaria": "", "genero": "M"}, "cargo": {"superioresids": [], "id": "74", "oficina": "Subsecretario de Seguridad Ciudadana", "electivo": false, "categoria": {"id": "74", "orden": 10, "nombre": "Subsecretario de Seguridad Ciudadana", "requiere_declaracion_jurada": true, "nombre_corto": "Subsecretario de Seguridad Ciudadana"}, "depende_de": "61", "nombre": "Subsecretario de Seguridad Ciudadana"}}, {"decreto_pdf": "", "decreto_nro": null, "fecha_inicio": "", "fecha_fin": "", "id": "75", "funcionario": {"edad": 0, "foto": {"original": "https://goo.gl/7k97nP", "thumbnail_32x32": "https://goo.gl/7k97nP", "thumbnail": "https://goo.gl/7k97nP"}, "apellido": "", "url": "", "uniqueid": "", "nombrepublico": "Cra. Daniela Lucarelli", "nombre": "Cra. Daniela Lucarelli", "franjaetaria": "", "genero": "F"}, "cargo": {"superioresids": [], "id": "75", "oficina": "Secretaria de Econom\u00eda y Finanzas", "electivo": false, "categoria": {"id": "75", "orden": 10, "nombre": "Secretaria de Econom\u00eda y Finanzas", "requiere_declaracion_jurada": true, "nombre_corto": "Secretaria de Econom\u00eda y Finanzas"}, "depende_de": "1", "nombre": "Secretaria de Econom\u00eda y Finanzas"}}, {"decreto_pdf": "", "decreto_nro": null, "fecha_inicio": "", "fecha_fin": "", "id": "76", "funcionario": {"edad": 0, "foto": {"original": "https://goo.gl/7k97nP", "thumbnail_32x32": "https://goo.gl/7k97nP", "thumbnail": "https://goo.gl/7k97nP"}, "apellido": "", "url": "", "uniqueid": "", "nombrepublico": "Cr. David Alejandro Bianchi", "nombre": "Cr. David Alejandro Bianchi", "franjaetaria": "", "genero": "M"}, "cargo": {"superioresids": [], "id": "76", "oficina": "Coordinador del Departamento de Transparencia y Control de Gesti\u00f3n", "electivo": false, "categoria": {"id": "76", "orden": 10, "nombre": "Coordinador del Departamento de Transparencia y Control de Gesti\u00f3n", "requiere_declaracion_jurada": true, "nombre_corto": "Coordinador del Departamento de Transparencia y Control de Gesti\u00f3n"}, "depende_de": "75", "nombre": "Coordinador del Departamento de Transparencia y Control de Gesti\u00f3n"}}, {"decreto_pdf": "", "decreto_nro": null, "fecha_inicio": "", "fecha_fin": "", "id": "77", "funcionario": {"edad": 0, "foto": {"original": "https://goo.gl/7k97nP", "thumbnail_32x32": "https://goo.gl/7k97nP", "thumbnail": "https://goo.gl/7k97nP"}, "apellido": "", "url": "", "uniqueid": "", "nombrepublico": "Cr. Pablo Peretti", "nombre": "Cr. Pablo Peretti", "franjaetaria": "", "genero": "M"}, "cargo": {"superioresids": [], "id": "77", "oficina": "Coordinador del Departamento de Modernizaci\u00f3n del Estado", "electivo": false, "categoria": {"id": "77", "orden": 10, "nombre": "Coordinador del Departamento de Modernizaci\u00f3n del Estado", "requiere_declaracion_jurada": true, "nombre_corto": "Coordinador del Departamento de Modernizaci\u00f3n del Estado"}, "depende_de": "75", "nombre": "Coordinador del Departamento de Modernizaci\u00f3n del Estado"}}, {"decreto_pdf": "", "decreto_nro": null, "fecha_inicio": "", "fecha_fin": "", "id": "78", "funcionario": {"edad": 0, "foto": {"original": "https://goo.gl/7k97nP", "thumbnail_32x32": "https://goo.gl/7k97nP", "thumbnail": "https://goo.gl/7k97nP"}, "apellido": "", "url": "", "uniqueid": "", "nombrepublico": "Cr. Rodolfo Eduardo Diana", "nombre": "Cr. Rodolfo Eduardo Diana", "franjaetaria": "", "genero": "M"}, "cargo": {"superioresids": [], "id": "78", "oficina": "Coordinador General de Compras, Stock y Aprovisionamiento", "electivo": false, "categoria": {"id": "78", "orden": 10, "nombre": "Coordinador General de Compras, Stock y Aprovisionamiento", "requiere_declaracion_jurada": true, "nombre_corto": "Coordinador General de Compras, Stock y Aprovisionamiento"}, "depende_de": "75", "nombre": "Coordinador General de Compras, Stock y Aprovisionamiento"}}, {"decreto_pdf": "", "decreto_nro": null, "fecha_inicio": "", "fecha_fin": "", "id": "79", "funcionario": {"edad": 0, "foto": {"original": "https://goo.gl/7k97nP", "thumbnail_32x32": "https://goo.gl/7k97nP", "thumbnail": "https://goo.gl/7k97nP"}, "apellido": "", "url": "", "uniqueid": "", "nombrepublico": "Cra. Romina Rico", "nombre": "Cra. Romina Rico", "franjaetaria": "", "genero": "F"}, "cargo": {"superioresids": [], "id": "79", "oficina": "Director de Contrataciones", "electivo": false, "categoria": {"id": "79", "orden": 10, "nombre": "Director de Contrataciones", "requiere_declaracion_jurada": true, "nombre_corto": "Director de Contrataciones"}, "depende_de": "75", "nombre": "Director de Contrataciones"}}, {"decreto_pdf": "", "decreto_nro": null, "fecha_inicio": "", "fecha_fin": "", "id": "80", "funcionario": {"edad": 0, "foto": {"original": "https://goo.gl/7k97nP", "thumbnail_32x32": "https://goo.gl/7k97nP", "thumbnail": "https://goo.gl/7k97nP"}, "apellido": "", "url": "", "uniqueid": "", "nombrepublico": "Cra. Carola Garc\u00eda", "nombre": "Cra. Carola Garc\u00eda", "franjaetaria": "", "genero": "F"}, "cargo": {"superioresids": [], "id": "80", "oficina": "Directora de Administraci\u00f3n y Gesti\u00f3n Econ\u00f3mica", "electivo": false, "categoria": {"id": "80", "orden": 10, "nombre": "Directora de Administraci\u00f3n y Gesti\u00f3n Econ\u00f3mica", "requiere_declaracion_jurada": true, "nombre_corto": "Directora de Administraci\u00f3n y Gesti\u00f3n Econ\u00f3mica"}, "depende_de": "75", "nombre": "Directora de Administraci\u00f3n y Gesti\u00f3n Econ\u00f3mica"}}, {"decreto_pdf": "", "decreto_nro": null, "fecha_inicio": "", "fecha_fin": "", "id": "81", "funcionario": {"edad": 0, "foto": {"original": "https://goo.gl/7k97nP", "thumbnail_32x32": "https://goo.gl/7k97nP", "thumbnail": "https://goo.gl/7k97nP"}, "apellido": "", "url": "", "uniqueid": "", "nombrepublico": "Cra. Eliana Anino", "nombre": "Cra. Eliana Anino", "franjaetaria": "", "genero": "F"}, "cargo": {"superioresids": [], "id": "81", "oficina": "Directora de Presupuesto", "electivo": false, "categoria": {"id": "81", "orden": 10, "nombre": "Directora de Presupuesto", "requiere_declaracion_jurada": true, "nombre_corto": "Directora de Presupuesto"}, "depende_de": "80", "nombre": "Directora de Presupuesto"}}, {"decreto_pdf": "", "decreto_nro": null, "fecha_inicio": "", "fecha_fin": "", "id": "82", "funcionario": {"edad": 0, "foto": {"original": "https://goo.gl/7k97nP", "thumbnail_32x32": "https://goo.gl/7k97nP", "thumbnail": "https://goo.gl/7k97nP"}, "apellido": "", "url": "", "uniqueid": "", "nombrepublico": "Cr. Lucas Ateca", "nombre": "Cr. Lucas Ateca", "franjaetaria": "", "genero": "M"}, "cargo": {"superioresids": [], "id": "82", "oficina": "Subsecretario de Ingresos P\u00fablicos", "electivo": false, "categoria": {"id": "82", "orden": 10, "nombre": "Subsecretario de Ingresos P\u00fablicos", "requiere_declaracion_jurada": true, "nombre_corto": "Subsecretario de Ingresos P\u00fablicos"}, "depende_de": "75", "nombre": "Subsecretario de Ingresos P\u00fablicos"}}, {"decreto_pdf": "", "decreto_nro": null, "fecha_inicio": "", "fecha_fin": "", "id": "83", "funcionario": {"edad": 0, "foto": {"original": "https://goo.gl/7k97nP", "thumbnail_32x32": "https://goo.gl/7k97nP", "thumbnail": "https://goo.gl/7k97nP"}, "apellido": "", "url": "", "uniqueid": "", "nombrepublico": "Dra. Margarita Schweizer", "nombre": "Dra. Margarita Schweizer", "franjaetaria": "", "genero": "F"}, "cargo": {"superioresids": [], "id": "83", "oficina": "Secretar\u00eda de Educaci\u00f3n", "electivo": false, "categoria": {"id": "83", "orden": 10, "nombre": "Secretar\u00eda de Educaci\u00f3n", "requiere_declaracion_jurada": true, "nombre_corto": "Secretar\u00eda de Educaci\u00f3n"}, "depende_de": "1", "nombre": "Secretar\u00eda de Educaci\u00f3n"}}, {"decreto_pdf": "", "decreto_nro": null, "fecha_inicio": "", "fecha_fin": "", "id": "84", "funcionario": {"edad": 0, "foto": {"original": "https://goo.gl/7k97nP", "thumbnail_32x32": "https://goo.gl/7k97nP", "thumbnail": "https://goo.gl/7k97nP"}, "apellido": "", "url": "", "uniqueid": "", "nombrepublico": "Prof. Mariela Paj\u00f3n", "nombre": "Prof. Mariela Paj\u00f3n", "franjaetaria": "", "genero": "F"}, "cargo": {"superioresids": [], "id": "84", "oficina": "Subsecretaria de Educaci\u00f3n Inicial", "electivo": false, "categoria": {"id": "84", "orden": 10, "nombre": "Subsecretaria de Educaci\u00f3n Inicial", "requiere_declaracion_jurada": true, "nombre_corto": "Subsecretaria de Educaci\u00f3n Inicial"}, "depende_de": "83", "nombre": "Subsecretaria de Educaci\u00f3n Inicial"}}, {"decreto_pdf": "", "decreto_nro": null, "fecha_inicio": "", "fecha_fin": "", "id": "85", "funcionario": {"edad": 0, "foto": {"original": "https://goo.gl/7k97nP", "thumbnail_32x32": "https://goo.gl/7k97nP", "thumbnail": "https://goo.gl/7k97nP"}, "apellido": "", "url": "", "uniqueid": "", "nombrepublico": "Javier Suppo", "nombre": "Javier Suppo", "franjaetaria": "", "genero": "M"}, "cargo": {"superioresids": [], "id": "85", "oficina": "Presidente del Ente para el Desarrollo Productivo y Tecnol\u00f3gico", "electivo": false, "categoria": {"id": "85", "orden": 10, "nombre": "Presidente del Ente para el Desarrollo Productivo y Tecnol\u00f3gico", "requiere_declaracion_jurada": true, "nombre_corto": "Presidente del Ente para el Desarrollo Productivo y Tecnol\u00f3gico"}, "depende_de": "0", "nombre": "Presidente del Ente para el Desarrollo Productivo y Tecnol\u00f3gico"}}, {"decreto_pdf": "", "decreto_nro": null, "fecha_inicio": "", "fecha_fin": "", "id": "86", "funcionario": {"edad": 0, "foto": {"original": "https://goo.gl/7k97nP", "thumbnail_32x32": "https://goo.gl/7k97nP", "thumbnail": "https://goo.gl/7k97nP"}, "apellido": "", "url": "", "uniqueid": "", "nombrepublico": "Cr. Alejandro Coschica", "nombre": "Cr. Alejandro Coschica", "franjaetaria": "", "genero": "M"}, "cargo": {"superioresids": [], "id": "86", "oficina": "", "electivo": false, "categoria": {"id": "86", "orden": 10, "nombre": "", "requiere_declaracion_jurada": true, "nombre_corto": ""}, "depende_de": "", "nombre": ""}}, {"decreto_pdf": "", "decreto_nro": null, "fecha_inicio": "", "fecha_fin": "", "id": "87", "funcionario": {"edad": 0, "foto": {"original": "https://goo.gl/7k97nP", "thumbnail_32x32": "https://goo.gl/7k97nP", "thumbnail": "https://goo.gl/7k97nP"}, "apellido": "", "url": "", "uniqueid": "", "nombrepublico": "Pablo Paris", "nombre": "Pablo Paris", "franjaetaria": "", "genero": "M"}, "cargo": {"superioresids": [], "id": "87", "oficina": "Director de Oficina de Empleo", "electivo": false, "categoria": {"id": "87", "orden": 10, "nombre": "Director de Oficina de Empleo", "requiere_declaracion_jurada": true, "nombre_corto": "Director de Oficina de Empleo"}, "depende_de": "85", "nombre": "Director de Oficina de Empleo"}}, {"decreto_pdf": "", "decreto_nro": null, "fecha_inicio": "", "fecha_fin": "", "id": "88", "funcionario": {"edad": 0, "foto": {"original": "https://goo.gl/7k97nP", "thumbnail_32x32": "https://goo.gl/7k97nP", "thumbnail": "https://goo.gl/7k97nP"}, "apellido": "", "url": "", "uniqueid": "", "nombrepublico": "Lic. Marcos Bovo", "nombre": "Lic. Marcos Bovo", "franjaetaria": "", "genero": "M"}, "cargo": {"superioresids": [], "id": "88", "oficina": "Presidente Unidad Ejecutora Villa Mar\u00eda Deporte y Turismo SEM", "electivo": false, "categoria": {"id": "88", "orden": 10, "nombre": "Presidente Unidad Ejecutora Villa Mar\u00eda Deporte y Turismo SEM", "requiere_declaracion_jurada": true, "nombre_corto": "Presidente Unidad Ejecutora Villa Mar\u00eda Deporte y Turismo SEM"}, "depende_de": "0", "nombre": "Presidente Unidad Ejecutora Villa Mar\u00eda Deporte y Turismo SEM"}}, {"decreto_pdf": "", "decreto_nro": null, "fecha_inicio": "", "fecha_fin": "", "id": "89", "funcionario": {"edad": 0, "foto": {"original": "https://goo.gl/7k97nP", "thumbnail_32x32": "https://goo.gl/7k97nP", "thumbnail": "https://goo.gl/7k97nP"}, "apellido": "", "url": "", "uniqueid": "", "nombrepublico": "Prof. Fernando Badr\u00e1n", "nombre": "Prof. Fernando Badr\u00e1n", "franjaetaria": "", "genero": "M"}, "cargo": {"superioresids": [], "id": "89", "oficina": "Director de Deportes", "electivo": false, "categoria": {"id": "89", "orden": 10, "nombre": "Director de Deportes", "requiere_declaracion_jurada": true, "nombre_corto": "Director de Deportes"}, "depende_de": "88", "nombre": "Director de Deportes"}}, {"decreto_pdf": "", "decreto_nro": null, "fecha_inicio": "", "fecha_fin": "", "id": "90", "funcionario": {"edad": 0, "foto": {"original": "https://goo.gl/7k97nP", "thumbnail_32x32": "https://goo.gl/7k97nP", "thumbnail": "https://goo.gl/7k97nP"}, "apellido": "", "url": "", "uniqueid": "", "nombrepublico": "Cr. Carlos Azzaretti", "nombre": "Cr. Carlos Azzaretti", "franjaetaria": "", "genero": "M"}, "cargo": {"superioresids": [], "id": "90", "oficina": "Director de Turismo", "electivo": false, "categoria": {"id": "90", "orden": 10, "nombre": "Director de Turismo", "requiere_declaracion_jurada": true, "nombre_corto": "Director de Turismo"}, "depende_de": "88", "nombre": "Director de Turismo"}}, {"decreto_pdf": "", "decreto_nro": null, "fecha_inicio": "", "fecha_fin": "", "id": "91", "funcionario": {"edad": 0, "foto": {"original": "https://goo.gl/7k97nP", "thumbnail_32x32": "https://goo.gl/7k97nP", "thumbnail": "https://goo.gl/7k97nP"}, "apellido": "", "url": "", "uniqueid": "", "nombrepublico": "Rodolfo Banchio", "nombre": "Rodolfo Banchio", "franjaetaria": "", "genero": "M"}, "cargo": {"superioresids": [], "id": "91", "oficina": "Ente Parque Industrial y Tecnol\u00f3gico Villa Mar\u00eda SEM", "electivo": false, "categoria": {"id": "91", "orden": 10, "nombre": "Ente Parque Industrial y Tecnol\u00f3gico Villa Mar\u00eda SEM", "requiere_declaracion_jurada": true, "nombre_corto": "Ente Parque Industrial y Tecnol\u00f3gico Villa Mar\u00eda SEM"}, "depende_de": "0", "nombre": "Ente Parque Industrial y Tecnol\u00f3gico Villa Mar\u00eda SEM"}}, {"decreto_pdf": "", "decreto_nro": null, "fecha_inicio": "", "fecha_fin": "", "id": "92", "funcionario": {"edad": 0, "foto": {"original": "https://goo.gl/7k97nP", "thumbnail_32x32": "https://goo.gl/7k97nP", "thumbnail": "https://goo.gl/7k97nP"}, "apellido": "", "url": "", "uniqueid": "", "nombrepublico": "Cra. Alejandra Barbero", "nombre": "Cra. Alejandra Barbero", "franjaetaria": "", "genero": "F"}, "cargo": {"superioresids": [], "id": "92", "oficina": "Gerenta del Parque Industrial y Tecnol\u00f3gico Villa Mar\u00eda SEM", "electivo": false, "categoria": {"id": "92", "orden": 10, "nombre": "Gerenta del Parque Industrial y Tecnol\u00f3gico Villa Mar\u00eda SEM", "requiere_declaracion_jurada": true, "nombre_corto": "Gerenta del Parque Industrial y Tecnol\u00f3gico Villa Mar\u00eda SEM"}, "depende_de": "0", "nombre": "Gerenta del Parque Industrial y Tecnol\u00f3gico Villa Mar\u00eda SEM"}}, {"decreto_pdf": "", "decreto_nro": null, "fecha_inicio": "", "fecha_fin": "", "id": "93", "funcionario": {"edad": 0, "foto": {"original": "https://goo.gl/7k97nP", "thumbnail_32x32": "https://goo.gl/7k97nP", "thumbnail": "https://goo.gl/7k97nP"}, "apellido": "", "url": "", "uniqueid": "", "nombrepublico": "Dr. Julio Oyola", "nombre": "Dr. Julio Oyola", "franjaetaria": "", "genero": "M"}, "cargo": {"superioresids": [], "id": "93", "oficina": "Presidente del Tribunal de Cuentas", "electivo": false, "categoria": {"id": "93", "orden": 10, "nombre": "Presidente del Tribunal de Cuentas", "requiere_declaracion_jurada": true, "nombre_corto": "Presidente del Tribunal de Cuentas"}, "depende_de": "0", "nombre": "Presidente del Tribunal de Cuentas"}}, {"decreto_pdf": "", "decreto_nro": null, "fecha_inicio": "", "fecha_fin": "", "id": "94", "funcionario": {"edad": 0, "foto": {"original": "https://goo.gl/7k97nP", "thumbnail_32x32": "https://goo.gl/7k97nP", "thumbnail": "https://goo.gl/7k97nP"}, "apellido": "", "url": "", "uniqueid": "", "nombrepublico": "Cra. Mariela Boaglio", "nombre": "Cra. Mariela Boaglio", "franjaetaria": "", "genero": "F"}, "cargo": {"superioresids": [], "id": "94", "oficina": "Vocal del Tribunal de Cuentas", "electivo": false, "categoria": {"id": "94", "orden": 10, "nombre": "Vocal del Tribunal de Cuentas", "requiere_declaracion_jurada": true, "nombre_corto": "Vocal del Tribunal de Cuentas"}, "depende_de": "93", "nombre": "Vocal del Tribunal de Cuentas"}}, {"decreto_pdf": "", "decreto_nro": null, "fecha_inicio": "", "fecha_fin": "", "id": "95", "funcionario": {"edad": 0, "foto": {"original": "https://goo.gl/7k97nP", "thumbnail_32x32": "https://goo.gl/7k97nP", "thumbnail": "https://goo.gl/7k97nP"}, "apellido": "", "url": "", "uniqueid": "", "nombrepublico": "Abog. Patricia G\u00f3mez", "nombre": "Abog. Patricia G\u00f3mez", "franjaetaria": "", "genero": "F"}, "cargo": {"superioresids": [], "id": "95", "oficina": "Vocal del Tribunal de Cuentas", "electivo": false, "categoria": {"id": "95", "orden": 10, "nombre": "Vocal del Tribunal de Cuentas", "requiere_declaracion_jurada": true, "nombre_corto": "Vocal del Tribunal de Cuentas"}, "depende_de": "93", "nombre": "Vocal del Tribunal de Cuentas"}}, {"decreto_pdf": "", "decreto_nro": null, "fecha_inicio": "", "fecha_fin": "", "id": "96", "funcionario": {"edad": 0, "foto": {"original": "https://goo.gl/7k97nP", "thumbnail_32x32": "https://goo.gl/7k97nP", "thumbnail": "https://goo.gl/7k97nP"}, "apellido": "", "url": "", "uniqueid": "", "nombrepublico": "Cr. Ricardo Faure", "nombre": "Cr. Ricardo Faure", "franjaetaria": "", "genero": "M"}, "cargo": {"superioresids": [], "id": "96", "oficina": "Secretario T\u00e9cnico", "electivo": false, "categoria": {"id": "96", "orden": 10, "nombre": "Secretario T\u00e9cnico", "requiere_declaracion_jurada": true, "nombre_corto": "Secretario T\u00e9cnico"}, "depende_de": "93", "nombre": "Secretario T\u00e9cnico"}}, {"decreto_pdf": "", "decreto_nro": null, "fecha_inicio": "", "fecha_fin": "", "id": "97", "funcionario": {"edad": 0, "foto": {"original": "https://goo.gl/7k97nP", "thumbnail_32x32": "https://goo.gl/7k97nP", "thumbnail": "https://goo.gl/7k97nP"}, "apellido": "", "url": "", "uniqueid": "", "nombrepublico": "Abog. Susana Chiapella", "nombre": "Abog. Susana Chiapella", "franjaetaria": "", "genero": "F"}, "cargo": {"superioresids": [], "id": "97", "oficina": "Secretaria T\u00e9cnica", "electivo": false, "categoria": {"id": "97", "orden": 10, "nombre": "Secretaria T\u00e9cnica", "requiere_declaracion_jurada": true, "nombre_corto": "Secretaria T\u00e9cnica"}, "depende_de": "93", "nombre": "Secretaria T\u00e9cnica"}}, {"decreto_pdf": "", "decreto_nro": null, "fecha_inicio": "", "fecha_fin": "", "id": null, "funcionario": {"edad": 0, "foto": {"original": "https://goo.gl/7k97nP", "thumbnail_32x32": "https://goo.gl/7k97nP", "thumbnail": "https://goo.gl/7k97nP"}, "apellido": "", "url": "", "uniqueid": "", "nombrepublico": "", "nombre": "", "franjaetaria": "", "genero": ""}, "cargo": {"superioresids": [], "id": null, "oficina": "", "electivo": false, "categoria": {"id": null, "orden": 10, "nombre": "", "requiere_declaracion_jurada": true, "nombre_corto": ""}, "depende_de": "", "nombre": ""}}, {"decreto_pdf": "", "decreto_nro": null, "fecha_inicio": "", "fecha_fin": "", "id": null, "funcionario": {"edad": 0, "foto": {"original": "https://goo.gl/7k97nP", "thumbnail_32x32": "https://goo.gl/7k97nP", "thumbnail": "https://goo.gl/7k97nP"}, "apellido": "", "url": "", "uniqueid": "", "nombrepublico": "", "nombre": "", "franjaetaria": "", "genero": "37"}, "cargo": {"superioresids": [], "id": null, "oficina": "", "electivo": false, "categoria": {"id": null, "orden": 10, "nombre": "", "requiere_declaracion_jurada": true, "nombre_corto": ""}, "depende_de": "Mujeres", "nombre": ""}}, {"decreto_pdf": "", "decreto_nro": null, "fecha_inicio": "", "fecha_fin": "", "id": null, "funcionario": {"edad": 0, "foto": {"original": "https://goo.gl/7k97nP", "thumbnail_32x32": "https://goo.gl/7k97nP", "thumbnail": "https://goo.gl/7k97nP"}, "apellido": "", "url": "", "uniqueid": "", "nombrepublico": "", "nombre": "", "franjaetaria": "", "genero": "60"}, "cargo": {"superioresids": [], "id": null, "oficina": "", "electivo": false, "categoria": {"id": null, "orden": 10, "nombre": "", "requiere_declaracion_jurada": true, "nombre_corto": ""}, "depende_de": "Hombres", "nombre": ""}}, {"decreto_pdf": "", "decreto_nro": null, "fecha_inicio": "", "fecha_fin": "", "id": null, "funcionario": {"edad": 0, "foto": {"original": "https://goo.gl/7k97nP", "thumbnail_32x32": "https://goo.gl/7k97nP", "thumbnail": "https://goo.gl/7k97nP"}, "apellido": "", "url": "", "uniqueid": "", "nombrepublico": "", "nombre": "", "franjaetaria": "", "genero": "38,14%"}, "cargo": {"superioresids": [], "id": null, "oficina": "Entidad acefala", "electivo": false, "categoria": {"id": null, "orden": 10, "nombre": "Entidad acefala", "requiere_declaracion_jurada": true, "nombre_corto": "Entidad acefala"}, "depende_de": "% mujeres", "nombre": "Entidad acefala"}}, {"decreto_pdf": "", "decreto_nro": null, "fecha_inicio": "", "fecha_fin": "", "id": null, "funcionario": {"edad": 0, "foto": {"original": "https://goo.gl/7k97nP", "thumbnail_32x32": "https://goo.gl/7k97nP", "thumbnail": "https://goo.gl/7k97nP"}, "apellido": "", "url": "", "uniqueid": "", "nombrepublico": "", "nombre": "", "franjaetaria": "", "genero": ""}, "cargo": {"superioresids": [], "id": null, "oficina": "Ente de deporte y turismo ", "electivo": false, "categoria": {"id": null, "orden": 10, "nombre": "Ente de deporte y turismo ", "requiere_declaracion_jurada": true, "nombre_corto": "Ente de deporte y turismo "}, "depende_de": "", "nombre": "Ente de deporte y turismo "}}, {"decreto_pdf": "", "decreto_nro": null, "fecha_inicio": "", "fecha_fin": "", "id": null, "funcionario": {"edad": 0, "foto": {"original": "https://goo.gl/7k97nP", "thumbnail_32x32": "https://goo.gl/7k97nP", "thumbnail": "https://goo.gl/7k97nP"}, "apellido": "", "url": "", "uniqueid": "", "nombrepublico": "", "nombre": "", "franjaetaria": "", "genero": ""}, "cargo": {"superioresids": [], "id": null, "oficina": "No existen m\u00e1s", "electivo": false, "categoria": {"id": null, "orden": 10, "nombre": "No existen m\u00e1s", "requiere_declaracion_jurada": true, "nombre_corto": "No existen m\u00e1s"}, "depende_de": "", "nombre": "No existen m\u00e1s"}}], "count": 97}